src/design/module_display.sv
module display (
    input logic [3 : 0] binary_code,      // Entrada: Código en binario
    output logic [6 : 0] display_code     // Salida: Código para el display
);
// Definición de las señales para cada segmento

    //Segmento A:
    assign display_code[6] = (~binary_code[0] & ~binary_code[1] & ~binary_code[2] & ~binary_code[3]) | //n0
                             (~binary_code[0] & binary_code[1] & ~binary_code[2] & ~binary_code[3]) |  //n2
                             (binary_code[0] & binary_code[1] & ~binary_code[2] & ~binary_code[3]) |   //n3
                             (binary_code[0] & ~binary_code[1] & binary_code[2] & ~binary_code[3]) |   //n5
                             (~binary_code[0] & binary_code[1] & binary_code[2] & ~binary_code[3]) |   //n6
                             (binary_code[0] & binary_code[1] & binary_code[2] & ~binary_code[3]) |    //n7
                             (~binary_code[0] & ~binary_code[1] & ~binary_code[2] & binary_code[3]) |  //n8
                             (binary_code[0] & ~binary_code[1] & ~binary_code[2] & binary_code[3]);    //n9

    //Segmento B:
    assign display_code[5] = (~binary_code[0] & ~binary_code[1] & ~binary_code[2] & ~binary_code[3]) | //n0
                             (binary_code[0] & ~binary_code[1] & ~binary_code[2] & ~binary_code[3]) |  //n1
                             (~binary_code[0] & binary_code[1] & ~binary_code[2] & ~binary_code[3]) |  //n2
                             (binary_code[0] & binary_code[1] & ~binary_code[2] & ~binary_code[3]) |   //n3
                             (~binary_code[0] & ~binary_code[1] & binary_code[2] & ~binary_code[3]) |  //n4
                             (binary_code[0] & binary_code[1] & binary_code[2] & ~binary_code[3]) |    //n7
                             (~binary_code[0] & ~binary_code[1] & ~binary_code[2] & binary_code[3]) |  //n8
                             (binary_code[0] & ~binary_code[1] & ~binary_code[2] & binary_code[3]);    //n9

    //Segmento C:
    assign display_code[4] = (~binary_code[0] & ~binary_code[1] & ~binary_code[2] & ~binary_code[3]) | //n0
                             (binary_code[0] & ~binary_code[1] & ~binary_code[2] & ~binary_code[3]) |  //n1
                             (binary_code[0] & binary_code[1] & ~binary_code[2] & ~binary_code[3]) |   //n3
                             (~binary_code[0] & ~binary_code[1] & binary_code[2] & ~binary_code[3]) |  //n4
                             (binary_code[0] & ~binary_code[1] & binary_code[2] & ~binary_code[3]) |   //n5
                             (~binary_code[0] & binary_code[1] & binary_code[2] & ~binary_code[3]) |   //n6
                             (binary_code[0] & binary_code[1] & binary_code[2] & ~binary_code[3]) |    //n7
                             (~binary_code[0] & ~binary_code[1] & ~binary_code[2] & binary_code[3]) |  //n8
                             (binary_code[0] & ~binary_code[1] & ~binary_code[2] & binary_code[3]);    //n9

    //Segmento D:
    assign display_code[3] = (~binary_code[0] & ~binary_code[1] & ~binary_code[2] & ~binary_code[3]) | //n0
                             (~binary_code[0] & binary_code[1] & ~binary_code[2] & ~binary_code[3]) |  //n2
                             (binary_code[0] & binary_code[1] & ~binary_code[2] & ~binary_code[3]) |   //n3
                             (binary_code[0] & ~binary_code[1] & binary_code[2] & ~binary_code[3]) |   //n5
                             (~binary_code[0] & binary_code[1] & binary_code[2] & ~binary_code[3]) |   //n6
                             (~binary_code[0] & ~binary_code[1] & ~binary_code[2] & binary_code[3]);   //n8

    //Segmento E:
    assign display_code[2] = (~binary_code[0] & ~binary_code[1] & ~binary_code[2] & ~binary_code[3]) | //n0
                             (~binary_code[0] & binary_code[1] & ~binary_code[2] & ~binary_code[3]) |  //n2
                             (~binary_code[0] & binary_code[1] & binary_code[2] & ~binary_code[3]) |   //n6
                             (~binary_code[0] & ~binary_code[1] & ~binary_code[2] & binary_code[3]);   //n8

    //Segmento F:
    assign display_code[1] = (~binary_code[0] & ~binary_code[1] & ~binary_code[2] & ~binary_code[3]) | //n0
                             (~binary_code[0] & ~binary_code[1] & binary_code[2] & ~binary_code[3]) |  //n4
                             (binary_code[0] & ~binary_code[1] & binary_code[2] & ~binary_code[3]) |   //n5
                             (~binary_code[0] & binary_code[1] & binary_code[2] & ~binary_code[3]) |   //n6
                             (~binary_code[0] & ~binary_code[1] & ~binary_code[2] & binary_code[3]) |  //n8
                             (binary_code[0] & ~binary_code[1] & ~binary_code[2] & binary_code[3]);    //n9

    //Segmento G:
    assign display_code[0] = (~binary_code[0] & binary_code[1] & ~binary_code[2] & ~binary_code[3]) |  //n2
                             (binary_code[0] & binary_code[1] & ~binary_code[2] & ~binary_code[3]) |   //n3
                             (~binary_code[0] & ~binary_code[1] & binary_code[2] & ~binary_code[3]) |  //n4
                             (binary_code[0] & ~binary_code[1] & binary_code[2] & ~binary_code[3]) |   //n5
                             (~binary_code[0] & binary_code[1] & binary_code[2] & ~binary_code[3]) |   //n6
                             (~binary_code[0] & ~binary_code[1] & ~binary_code[2] & binary_code[3]) |  //n8
                             (binary_code[0] & ~binary_code[1] & ~binary_code[2] & binary_code[3]);    //n9

endmodule

src/sim/tb_module_display.sv
// Archivo: tb_display.sv
module tb_display;

    // Señales
    reg [3:0] binary_code;
    wire [6:0] display_code;

    // Instanciación del módulo display
    display uut (
        .binary_code(binary_code),
        .display_code(display_code)
    );

    // Inicialización y estímulos
    initial begin
        // Aplicar todos los valores binarios posibles
        binary_code = 4'b0000; #10; $display("Binary: %b, Display: %b", binary_code, display_code);
        binary_code = 4'b0001; #10; $display("Binary: %b, Display: %b", binary_code, display_code);
        binary_code = 4'b0010; #10; $display("Binary: %b, Display: %b", binary_code, display_code);
        binary_code = 4'b0011; #10; $display("Binary: %b, Display: %b", binary_code, display_code);
        binary_code = 4'b0100; #10; $display("Binary: %b, Display: %b", binary_code, display_code);
        binary_code = 4'b0101; #10; $display("Binary: %b, Display: %b", binary_code, display_code);
        binary_code = 4'b0110; #10; $display("Binary: %b, Display: %b", binary_code, display_code);
        binary_code = 4'b0111; #10; $display("Binary: %b, Display: %b", binary_code, display_code);
        binary_code = 4'b1000; #10; $display("Binary: %b, Display: %b", binary_code, display_code);
        binary_code = 4'b1001; #10; $display("Binary: %b, Display: %b", binary_code, display_code);

        // Terminar la simulación
        $finish;
    end

    // Dump de las señales a un archivo VCD
    initial begin
        $dumpfile("display_simulation.vcd"); // Nombre del archivo VCD
        $dumpvars(0, tb_display); // Dump de todas las señales del testbench
    end

endmodule

src/build/display_simulation.vcd
$date
	Sun Aug 25 08:44:16 2024
$end
$version
	Icarus Verilog
$end
$timescale
	1s
$end
$scope module tb_display $end
$var wire 7 ! display_code [6:0] $end
$var reg 4 " binary_code [3:0] $end
$scope module uut $end
$var wire 4 # binary_code [3:0] $end
$var wire 7 $ display_code [6:0] $end
$upscope $end
$upscope $end
$enddefinitions $end
$comment Show the parameter values. $end
$dumpall
$end
#0
$dumpvars
b1111110 $
b0 #
b0 "
b1111110 !
$end
#10
b110000 !
b110000 $
b1 "
b1 #
#20
b1101101 !
b1101101 $
b10 "
b10 #
#30
b1111001 !
b1111001 $
b11 "
b11 #
#40
b110011 !
b110011 $
b100 "
b100 #
#50
b1011011 !
b1011011 $
b101 "
b101 #
#60
b1011111 !
b1011111 $
b110 "
b110 #
#70
b1110000 !
b1110000 $
b111 "
b111 #
#80
b1111111 !
b1111111 $
b1000 "
b1000 #
#90
b1110011 !
b1110011 $
b1001 "
b1001 #
