src/design/gray_to_leds.sv
//Este modulo controla los datos enviados a los puertos de LEDs

module gray_to_leds (
    input logic [3:0] binary,       // Entrada binaria
    output logic [5:0] leds         // Salida para LEDs (6 LEDs)
);

    // Asignar los 4 bits del valor binario a los primeros 4 LEDs
    assign leds[3:0] = ~binary; //se niega la variable

    // Los últimos 2 LEDs apagados 
    assign leds[5:4] = 2'b11;

endmodule

src/design/gray_decoder.sv
module gray_decoder (
    input logic [3:0] gray,   // Entrada en Gray
    output logic [3:0] binary // Salida en Binario
);

    // Conversión de Gray a Binario
    assign binary[3] = gray[3];                // El bit más significativo es igual
    assign binary[2] = gray[3] ^ gray[2];      // bit2 = bit3 ^ bit2
    assign binary[1] = binary[2] ^ gray[1];   // bit1 = bit2 ^ bit1
    assign binary[0] = binary[1] ^ gray[0];   // bit0 = bit1 ^ bit0

endmodule

src/sim/tb_gray_to_leds.sv
module tb_gray_to_leds;

    // Señales
    reg [3:0] gray; // Entrada en Gray
    wire [3:0] binary; // Salida en Binario
    wire [5:0] leds; // Señales para los LEDs

    // Instanciación del módulo Gray Decoder
    gray_decoder uut_gray (
        .gray(gray),
        .binary(binary)
    );

    // Instanciación del módulo de despliegue en LEDs
    gray_to_leds uut_led (
        .binary(binary),
        .leds(leds)
    );

    // Inicialización y estímulos
    initial begin
        // Aplicar todos los valores Gray posibles y mostrar los resultados
        gray = 4'b0000; #10; $display("Gray: %b, Binary: %b, LEDs: %b", gray, binary, leds);
        gray = 4'b0001; #10; $display("Gray: %b, Binary: %b, LEDs: %b", gray, binary, leds);
        gray = 4'b0011; #10; $display("Gray: %b, Binary: %b, LEDs: %b", gray, binary, leds);
        gray = 4'b0010; #10; $display("Gray: %b, Binary: %b, LEDs: %b", gray, binary, leds);
        gray = 4'b0110; #10; $display("Gray: %b, Binary: %b, LEDs: %b", gray, binary, leds);
        gray = 4'b0111; #10; $display("Gray: %b, Binary: %b, LEDs: %b", gray, binary, leds);
        gray = 4'b0101; #10; $display("Gray: %b, Binary: %b, LEDs: %b", gray, binary, leds);
        gray = 4'b0100; #10; $display("Gray: %b, Binary: %b, LEDs: %b", gray, binary, leds);
        gray = 4'b1100; #10; $display("Gray: %b, Binary: %b, LEDs: %b", gray, binary, leds);
        gray = 4'b1101; #10; $display("Gray: %b, Binary: %b, LEDs: %b", gray, binary, leds);
        gray = 4'b1111; #10; $display("Gray: %b, Binary: %b, LEDs: %b", gray, binary, leds);
        gray = 4'b1110; #10; $display("Gray: %b, Binary: %b, LEDs: %b", gray, binary, leds);
        gray = 4'b1010; #10; $display("Gray: %b, Binary: %b, LEDs: %b", gray, binary, leds);
        gray = 4'b1011; #10; $display("Gray: %b, Binary: %b, LEDs: %b", gray, binary, leds);
        gray = 4'b1001; #10; $display("Gray: %b, Binary: %b, LEDs: %b", gray, binary, leds);
        gray = 4'b1000; #10; $display("Gray: %b, Binary: %b, LEDs: %b", gray, binary, leds);

        // Terminar la simulación
        $finish;
    end

    // Dump de las señales a un archivo VCD
    initial begin
        $dumpfile("simulation_combined.vcd"); // Nombre del archivo VCD
        $dumpvars(0, tb_gray_to_leds); // Dump de todas las señales del testbench
    end

endmodule

src/build/simulation_combined.vcd
$date
	Fri Aug 23 17:27:41 2024
$end
$version
	Icarus Verilog
$end
$timescale
	1s
$end
$scope module tb_gray_to_leds $end
$var wire 6 ! leds [5:0] $end
$var wire 4 " binary [3:0] $end
$var reg 4 # gray [3:0] $end
$scope module uut_gray $end
$var wire 4 $ gray [3:0] $end
$var wire 4 % binary [3:0] $end
$upscope $end
$scope module uut_led $end
$var wire 4 & binary [3:0] $end
$var wire 6 ' leds [5:0] $end
$upscope $end
$upscope $end
$enddefinitions $end
$comment Show the parameter values. $end
$dumpall
$end
#0
$dumpvars
b0 '
b0 &
b0 %
b0 $
b0 #
b0 "
b0 !
$end
#10
b1 !
b1 '
b1 "
b1 %
b1 &
b1 #
b1 $
#20
b10 !
b10 '
b10 "
b10 %
b10 &
b11 #
b11 $
#30
b11 !
b11 '
b11 "
b11 %
b11 &
b10 #
b10 $
#40
b100 !
b100 '
b100 "
b100 %
b100 &
b110 #
b110 $
#50
b101 !
b101 '
b101 "
b101 %
b101 &
b111 #
b111 $
#60
b110 !
b110 '
b110 "
b110 %
b110 &
b101 #
b101 $
#70
b111 !
b111 '
b111 "
b111 %
b111 &
b100 #
b100 $
#80
b1000 !
b1000 '
b1000 "
b1000 %
b1000 &
b1100 #
b1100 $
#90
b1001 !
b1001 '
b1001 "
b1001 %
b1001 &
b1101 #
b1101 $
#100
b1010 !
b1010 '
b1010 "
b1010 %
b1010 &
b1111 #
b1111 $
#110
b1011 !
b1011 '
b1011 "
b1011 %
b1011 &
b1110 #
b1110 $
#120
b1100 !
b1100 '
b1100 "
b1100 %
b1100 &
b1010 #
b1010 $
#130
b1101 !
b1101 '
b1101 "
b1101 %
b1101 &
b1011 #
b1011 $
#140
b1110 !
b1110 '
b1110 "
b1110 %
b1110 &
b1001 #
b1001 $
#150
b1111 !
b1111 '
b1111 "
b1111 %
b1111 &
b1000 #
b1000 $
