src/design/gray_decoder.sv
module gray_decoder (
    input logic [3:0] gray,   // Entrada en Gray
    output logic [3:0] binary // Salida en Binario
);

    // Conversión de Gray a Binario
    assign binary[3] = gray[3];                // El bit más significativo es igual
    assign binary[2] = gray[3] ^ gray[2];      // bit2 = bit3 ^ bit2
    assign binary[1] = binary[2] ^ gray[1];   // bit1 = bit2 ^ bit1
    assign binary[0] = binary[1] ^ gray[0];   // bit0 = bit1 ^ bit0

endmodule

src/sim/tb_gray_decoder.sv
module tb_gray_decoder;

    // Señales
    logic [3:0] gray;
    logic [3:0] binary;

    // Instanciación del módulo
    gray_decoder uut (
        .gray(gray),
        .binary(binary)
    );

    // Inicialización y estímulos
    initial begin
        // Aplicar toos los valores Gray posibles y mostrar los resultados
        gray = 4'b0000; #10; $display("Gray: %b, Binary: %b", gray, binary);
        gray = 4'b0001; #10; $display("Gray: %b, Binary: %b", gray, binary);
        gray = 4'b0011; #10; $display("Gray: %b, Binary: %b", gray, binary);
        gray = 4'b0010; #10; $display("Gray: %b, Binary: %b", gray, binary);
        gray = 4'b0110; #10; $display("Gray: %b, Binary: %b", gray, binary);
        gray = 4'b0111; #10; $display("Gray: %b, Binary: %b", gray, binary);
        gray = 4'b0101; #10; $display("Gray: %b, Binary: %b", gray, binary);
        gray = 4'b0100; #10; $display("Gray: %b, Binary: %b", gray, binary);
        gray = 4'b1100; #10; $display("Gray: %b, Binary: %b", gray, binary);
        gray = 4'b1101; #10; $display("Gray: %b, Binary: %b", gray, binary);
        gray = 4'b1111; #10; $display("Gray: %b, Binary: %b", gray, binary);
        gray = 4'b1110; #10; $display("Gray: %b, Binary: %b", gray, binary);
        gray = 4'b1010; #10; $display("Gray: %b, Binary: %b", gray, binary);
        gray = 4'b1011; #10; $display("Gray: %b, Binary: %b", gray, binary);
        gray = 4'b1001; #10; $display("Gray: %b, Binary: %b", gray, binary);
        gray = 4'b1000; #10; $display("Gray: %b, Binary: %b", gray, binary);

        // Terminar la simulación
        $finish;
    end

    // Dump de las señales a un archivo VCD
  initial begin
    $dumpfile("simulation.vcd"); // Nombre del archivo VCD
    $dumpvars(0, tb_gray_decoder); // Dump de todas las señales del testbench
  end

endmodule

src/build/simulation.vcd
$date
	Wed Aug 21 21:48:31 2024
$end
$version
	Icarus Verilog
$end
$timescale
	1s
$end
$scope module tb_gray_decoder $end
$var wire 4 ! binary [3:0] $end
$var reg 4 " gray [3:0] $end
$scope module uut $end
$var wire 4 # gray [3:0] $end
$var wire 4 $ binary [3:0] $end
$upscope $end
$upscope $end
$enddefinitions $end
$comment Show the parameter values. $end
$dumpall
$end
#0
$dumpvars
b0 $
b0 #
b0 "
b0 !
$end
#10
b1 !
b1 $
b1 "
b1 #
#20
b10 !
b10 $
b11 "
b11 #
#30
b11 !
b11 $
b10 "
b10 #
#40
b100 !
b100 $
b110 "
b110 #
#50
b101 !
b101 $
b111 "
b111 #
#60
b110 !
b110 $
b101 "
b101 #
#70
b111 !
b111 $
b100 "
b100 #
#80
b1000 !
b1000 $
b1100 "
b1100 #
#90
b1001 !
b1001 $
b1101 "
b1101 #
#100
b1010 !
b1010 $
b1111 "
b1111 #
#110
b1011 !
b1011 $
b1110 "
b1110 #
#120
b1100 !
b1100 $
b1010 "
b1010 #
#130
b1101 !
b1101 $
b1011 "
b1011 #
#140
b1110 !
b1110 $
b1001 "
b1001 #
#150
b1111 !
b1111 $
b1000 "
b1000 #
