src/design/module_display.sv
//Este modulo controla los datos enviados a los puertos del display

module display #(

    input logic [3 : 0] binary_code,      //Entrada: Codigo en binario
    output logic [6 : 0] display_code     //Salida: Codigo para el display
);

    //Segmento A:
    assign display_code[0] = ~((~binary_code[3] & ~binary_code[2] & ~binary_code[1] &  binary_code[0]) |
                              (~binary_code[3] &  binary_code[2] & ~binary_code[1] & ~binary_code[0]) |
                              ( binary_code[3] & ~binary_code[2] &  binary_code[1] &  binary_code[0]) |
                              ( binary_code[3] &  binary_code[2] & ~binary_code[1] &  binary_code[0]));

    //Segmento B:
    assign display_code[1] = ~((~binary_code[3] &  binary_code[2] & ~binary_code[1] &  binary_code[0]) | 
                              ( binary_code[3] &  binary_code[1] &  binary_code[0]) |
                              ( binary_code[2] &  binary_code[1] & ~binary_code[0]) |
                              ( binary_code[3] &  binary_code[2] & ~binary_code[0]));

    //Segmento C:
    assign display_code[2] = ~((~binary_code[3] & ~binary_code[2] &  binary_code[1] & ~binary_code[0]) | 
                              ( binary_code[3] &  binary_code[2] &  binary_code[1]) |
                              ( binary_code[3] &  binary_code[2] & ~binary_code[0]));

    //Segmento D:
    assign display_code[3] = ~((~binary_code[3] & ~binary_code[2] & ~binary_code[1] &  binary_code[0]) | 
                              (~binary_code[3] &  binary_code[2] & ~binary_code[1] & ~binary_code[0]) |
                              ( binary_code[2] &  binary_code[1] &  binary_code[0]) |
                              ( binary_code[3] & ~binary_code[2] &  binary_code[1] & ~binary_code[0]));

    //Segmento E:
    assign display_code[4] = ~((~binary_code[3] &  binary_code[0]) | 
                              (~binary_code[3] &  binary_code[2] & ~binary_code[1]) |
                              (~binary_code[2] & ~binary_code[1] &  binary_code[0]));

    //Segmento F:
    assign display_code[5] = ~((~binary_code[3] & ~binary_code[2] &  binary_code[0]) | 
                              (~binary_code[3] & ~binary_code[2] &  binary_code[1]) |
                              (~binary_code[3] &  binary_code[1] &  binary_code[0]) |
                              ( binary_code[3] &  binary_code[2] & ~binary_code[1] &  binary_code[0]));

    //Segmento G:
    assign display_code[6] = ~((~binary_code[3] & ~binary_code[2] & ~binary_code[1]) |
                              ( binary_code[3] &  binary_code[2] & ~binary_code[1] & ~binary_code[0]) |
                              (~binary_code[3] &  binary_code[2] &  binary_code[1] &  binary_code[0]));
endmodule

src/design/module_comparator.sv
//Este modulo compara si el numero binario es mayor o menor a 9

module comparator (

    input logic [3 : 0] binary_code,     
    output logic comparation
 
);
    //1. Comprobar si el binario es mayor o menor a 1001 (9) 
    //0 -> <9 y 1 -> >9
     assign comparation = binary_code[3] & (binary_code[2] | binary_code[1]);
     
endmodule

src/design/module_units.sv
//Extrae la unidad en numeros binarios mayores a 9

module units (
    input logic [3 : 0] binary_code,      //Entrada: codigo binario mayor a 9
    output logic [3 : 0] binary_units      //Salida: unidades del numero binario de entrada

);

assign binary_units = binary_code - 4'b1010;

endmodule

src/design/gray_to_leds.sv
//Este modulo controla los datos enviados a los puertos de LEDs

module gray_to_leds (
    input logic [3:0] binary,       // Entrada binaria
    output logic [5:0] leds         // Salida para LEDs (6 LEDs)
);

    // Asignar los 4 bits del valor binario a los primeros 4 LEDs
    assign leds[3:0] = ~binary; //se niega la variable

    // Los últimos 2 LEDs apagados 
    assign leds[5:4] = 2'b11;

endmodule

src/design/gray_decoder.sv
module gray_decoder (
    input logic [3:0] gray,   // Entrada en Gray
    output logic [3:0] binary // Salida en Binario
);

    // Conversión de Gray a Binario
    assign binary[3] = gray[3];                // El bit más significativo es igual
    assign binary[2] = gray[3] ^ gray[2];      // bit2 = bit3 ^ bit2
    assign binary[1] = binary[2] ^ gray[1];   // bit1 = bit2 ^ bit1
    assign binary[0] = binary[1] ^ gray[0];   // bit0 = bit1 ^ bit0

endmodule

src/design/module_top.sv
//Este módulo interconecta los sub módulos 

module top (

    input logic [3 : 0] gray_code,       //Entrada: codigo Gray
    input logic show_decades, 
    output logic [5:0] leds,           //Entrada: boton de decenas o unidades
    output logic [6 : 0] display_code   //Salida: codigo al display
);

    logic [3 : 0] binary_code;      //Almacena temporalmente el codigo binario
    logic [3 : 0] units_code;       //Almacena las unidades temporalmente
    logic [3 : 0] decades_code;     //Almacena las decenas temporalmente
    logic [3 : 0] selected_code;    //Guarda el codigo a entregar en el module_display
    logic show_units;               //Almacena 0 si <9 o 1 si >9

    gray_decoder u_gray_decoder (
        .gray(gray_code),           //Se recibe el código Gray y se envía a gray_decoder.sv
        .binary(binary_code)        //Recoge el codigo binario ya convertido y lo almacena
    );

    gray_to_leds u_gray_to_leds ( //Se despliega el numero binario resultante en los leds de la fpga
        .binary(binary_code),
        .leds(leds)
    );

    units u_module_units(
        .binary_code(binary_code),  //Envia el binario para separar unidades
        .binary_units(units_code)   //Almacena las unidades extraides
    );

    comparator u_module_comparator(
        .binary_code(binary_code),      //Le envia la señal en binario al module_display
        .comparation(show_units)                  //Indica si n<9 o n>9
    );

    //mux que va con el comparador (escoje que binario pasa al module display)
    assign decades_code = (show_units) ? 4'b0001 : 4'b0000; //Vale 1 si show_units == 1 y 0 si show_units == 0
    assign selected_code = (show_decades) ? decades_code : (show_units ? units_code : binary_code); //Determina el codigo a enviar

    display u_module_display(
        .binary_code(selected_code),
        .display_code(display_code)
    );
endmodule

src/sim/tb_module_top.sv
`timescale 1ns / 1ps

module tb_top;

    // Entradas para el módulo 'top'
    logic [3:0] gray_code;
    logic show_decades;

    // Salida del módulo 'top'
    logic [6:0] display_code;
    logic show_units;            // Wire para la señal show_units
    logic [3:0] comparation;     // Wire para la señal comparation

    // Instancia del módulo 'top'
    top uut (
        .gray_code(gray_code),
        .show_decades(show_decades),
        .display_code(display_code)
    );

    // Conectar las señales internas del módulo 'top' a los wires
    assign show_units = uut.show_units;
    //assign comparation = uut.show_units;

    // Generación de señales de prueba
    initial begin
        // Inicialización
        gray_code = 4'b0000;
        show_decades = 0;

        // Pruebas con show_decades = 0
        // Verifica que el display muestra el valor binario correcto para valores de 0 a 15
        #10 gray_code = 4'b0000; // 0
        #10 gray_code = 4'b0001; // 1
        #10 gray_code = 4'b0011; // 2
        #10 gray_code = 4'b0010; // 3
        #10 gray_code = 4'b0110; // 4
        #10 gray_code = 4'b0111; // 5
        #10 gray_code = 4'b0101; // 6
        #10 gray_code = 4'b0100; // 7
        #10 gray_code = 4'b1100; // 8
        #10 gray_code = 4'b1101; // 9
        #10 gray_code = 4'b1111; // 10
        #10 gray_code = 4'b1110; // 11
        #10 gray_code = 4'b1010; // 12
        #10 gray_code = 4'b1011; // 13
        #10 gray_code = 4'b1001; // 14
        #10 gray_code = 4'b1000; // 15

        // Cambio de show_decades a 1
        #10 show_decades = 1;

        // Pruebas con show_decades = 1
        // Verifica que el display muestra las decenas cuando el valor es mayor a 9
        #10 gray_code = 4'b0000; // 0
        #10 gray_code = 4'b0001; // 1
        #10 gray_code = 4'b0011; // 2
        #10 gray_code = 4'b0010; // 3
        #10 gray_code = 4'b0110; // 4
        #10 gray_code = 4'b0111; // 5
        #10 gray_code = 4'b0101; // 6
        #10 gray_code = 4'b0100; // 7
        #10 gray_code = 4'b1100; // 8
        #10 gray_code = 4'b1101; // 9
        #10 gray_code = 4'b1111; // 10
        #10 gray_code = 4'b1110; // 11
        #10 gray_code = 4'b1010; // 12
        #10 gray_code = 4'b1011; // 13
        #10 gray_code = 4'b1001; // 14
        #10 gray_code = 4'b1000; // 15

        // Finalización de la simulación
        #10 $finish;
    end

    // Monitorear las señales
    initial begin
        $monitor("At time %t: gray_code = %b, show_decades = %b, display_code = %b, show_units = %b",
                 $time, gray_code, show_decades, display_code, show_units);
    end

    // Dump de la simulación para VCD
    initial begin
        $dumpfile("tb_top_simulation.vcd");
        $dumpvars(0, tb_top);
    end

endmodule

src/build/tb_top_simulation.vcd
$date
	Tue Aug 27 16:26:03 2024
$end
$version
	Icarus Verilog
$end
$timescale
	1ps
$end
$scope module tb_top $end
$var wire 1 ! show_units $end
$var wire 7 " display_code [6:0] $end
$var reg 4 # gray_code [3:0] $end
$var reg 1 $ show_decades $end
$scope module uut $end
$var wire 4 % gray_code [3:0] $end
$var wire 1 $ show_decades $end
$var wire 4 & units_code [3:0] $end
$var wire 1 ' show_units $end
$var wire 4 ( selected_code [3:0] $end
$var wire 6 ) leds [5:0] $end
$var wire 7 * display_code [6:0] $end
$var wire 4 + decades_code [3:0] $end
$var wire 4 , binary_code [3:0] $end
$scope module u_gray_decoder $end
$var wire 4 - gray [3:0] $end
$var wire 4 . binary [3:0] $end
$upscope $end
$scope module u_gray_to_leds $end
$var wire 4 / binary [3:0] $end
$var wire 6 0 leds [5:0] $end
$upscope $end
$scope module u_module_comparator $end
$var wire 4 1 binary_code [3:0] $end
$var wire 1 ' comparation $end
$upscope $end
$scope module u_module_display $end
$var wire 4 2 binary_code [3:0] $end
$var wire 7 3 display_code [6:0] $end
$upscope $end
$scope module u_module_units $end
$var wire 4 4 binary_code [3:0] $end
$var wire 4 5 binary_units [3:0] $end
$upscope $end
$upscope $end
$upscope $end
$enddefinitions $end
$comment Show the parameter values. $end
$dumpall
$end
#0
$dumpvars
b110 5
b0 4
b1111110 3
b0 2
b0 1
b111111 0
b0 /
b0 .
b0 -
b0 ,
b0 +
b1111110 *
b111111 )
b0 (
0'
b110 &
b0 %
0$
b0 #
b1111110 "
0!
$end
#20000
b110000 "
b110000 *
b110000 3
b1 (
b1 2
b111110 )
b111110 0
b111 &
b111 5
b1 ,
b1 .
b1 /
b1 1
b1 4
b1 #
b1 %
b1 -
#30000
b1101101 "
b1101101 *
b1101101 3
b10 (
b10 2
b111101 )
b111101 0
b1000 &
b1000 5
b10 ,
b10 .
b10 /
b10 1
b10 4
b11 #
b11 %
b11 -
#40000
b1111001 "
b1111001 *
b1111001 3
b11 (
b11 2
b111100 )
b111100 0
b1001 &
b1001 5
b11 ,
b11 .
b11 /
b11 1
b11 4
b10 #
b10 %
b10 -
#50000
b110011 "
b110011 *
b110011 3
b100 (
b100 2
b111011 )
b111011 0
b1010 &
b1010 5
b100 ,
b100 .
b100 /
b100 1
b100 4
b110 #
b110 %
b110 -
#60000
b1011011 "
b1011011 *
b1011011 3
b101 (
b101 2
b111010 )
b111010 0
b1011 &
b1011 5
b101 ,
b101 .
b101 /
b101 1
b101 4
b111 #
b111 %
b111 -
#70000
b1011111 "
b1011111 *
b1011111 3
b110 (
b110 2
b111001 )
b111001 0
b1100 &
b1100 5
b110 ,
b110 .
b110 /
b110 1
b110 4
b101 #
b101 %
b101 -
#80000
b1110000 "
b1110000 *
b1110000 3
b111 (
b111 2
b111000 )
b111000 0
b1101 &
b1101 5
b111 ,
b111 .
b111 /
b111 1
b111 4
b100 #
b100 %
b100 -
#90000
b1111111 "
b1111111 *
b1111111 3
b0 +
0!
0'
b1000 (
b1000 2
b110111 )
b110111 0
b1110 &
b1110 5
b1000 ,
b1000 .
b1000 /
b1000 1
b1000 4
b1100 #
b1100 %
b1100 -
#100000
b1110011 "
b1110011 *
b1110011 3
b1001 (
b1001 2
b110110 )
b110110 0
b1111 &
b1111 5
b1001 ,
b1001 .
b1001 /
b1001 1
b1001 4
b1101 #
b1101 %
b1101 -
#110000
b1111110 "
b1111110 *
b1111110 3
b1 +
1!
1'
b0 (
b0 2
b110101 )
b110101 0
b0 &
b0 5
b1010 ,
b1010 .
b1010 /
b1010 1
b1010 4
b1111 #
b1111 %
b1111 -
#120000
b110000 "
b110000 *
b110000 3
b1 (
b1 2
b110100 )
b110100 0
b1 &
b1 5
b1011 ,
b1011 .
b1011 /
b1011 1
b1011 4
b1110 #
b1110 %
b1110 -
#130000
b1101101 "
b1101101 *
b1101101 3
b10 (
b10 2
b110011 )
b110011 0
b10 &
b10 5
b1100 ,
b1100 .
b1100 /
b1100 1
b1100 4
b1010 #
b1010 %
b1010 -
#140000
b1111001 "
b1111001 *
b1111001 3
b11 (
b11 2
b110010 )
b110010 0
b11 &
b11 5
b1101 ,
b1101 .
b1101 /
b1101 1
b1101 4
b1011 #
b1011 %
b1011 -
#150000
b110011 "
b110011 *
b110011 3
b100 (
b100 2
b110001 )
b110001 0
b100 &
b100 5
b1110 ,
b1110 .
b1110 /
b1110 1
b1110 4
b1001 #
b1001 %
b1001 -
#160000
b1011011 "
b1011011 *
b1011011 3
b101 (
b101 2
b110000 )
b110000 0
b101 &
b101 5
b1111 ,
b1111 .
b1111 /
b1111 1
b1111 4
b1000 #
b1000 %
b1000 -
#170000
b110000 "
b110000 *
b110000 3
b1 (
b1 2
1$
#180000
b1111110 "
b1111110 *
b1111110 3
b0 (
b0 2
b0 +
0!
0'
b111111 )
b111111 0
b110 &
b110 5
b0 ,
b0 .
b0 /
b0 1
b0 4
b0 #
b0 %
b0 -
#190000
b111110 )
b111110 0
b111 &
b111 5
b1 ,
b1 .
b1 /
b1 1
b1 4
b1 #
b1 %
b1 -
#200000
b111101 )
b111101 0
b1000 &
b1000 5
b10 ,
b10 .
b10 /
b10 1
b10 4
b11 #
b11 %
b11 -
#210000
b111100 )
b111100 0
b1001 &
b1001 5
b11 ,
b11 .
b11 /
b11 1
b11 4
b10 #
b10 %
b10 -
#220000
b111011 )
b111011 0
b1010 &
b1010 5
b100 ,
b100 .
b100 /
b100 1
b100 4
b110 #
b110 %
b110 -
#230000
b111010 )
b111010 0
b1011 &
b1011 5
b101 ,
b101 .
b101 /
b101 1
b101 4
b111 #
b111 %
b111 -
#240000
b111001 )
b111001 0
b1100 &
b1100 5
b110 ,
b110 .
b110 /
b110 1
b110 4
b101 #
b101 %
b101 -
#250000
b111000 )
b111000 0
b1101 &
b1101 5
b111 ,
b111 .
b111 /
b111 1
b111 4
b100 #
b100 %
b100 -
#260000
b1111110 "
b1111110 *
b1111110 3
b0 (
b0 2
b0 +
0!
0'
b110111 )
b110111 0
b1110 &
b1110 5
b1000 ,
b1000 .
b1000 /
b1000 1
b1000 4
b1100 #
b1100 %
b1100 -
#270000
b110110 )
b110110 0
b1111 &
b1111 5
b1001 ,
b1001 .
b1001 /
b1001 1
b1001 4
b1101 #
b1101 %
b1101 -
#280000
b110000 "
b110000 *
b110000 3
b1 (
b1 2
b1 +
1!
1'
b110101 )
b110101 0
b0 &
b0 5
b1010 ,
b1010 .
b1010 /
b1010 1
b1010 4
b1111 #
b1111 %
b1111 -
#290000
b110100 )
b110100 0
b1 &
b1 5
b1011 ,
b1011 .
b1011 /
b1011 1
b1011 4
b1110 #
b1110 %
b1110 -
#300000
b110011 )
b110011 0
b10 &
b10 5
b1100 ,
b1100 .
b1100 /
b1100 1
b1100 4
b1010 #
b1010 %
b1010 -
#310000
b110010 )
b110010 0
b11 &
b11 5
b1101 ,
b1101 .
b1101 /
b1101 1
b1101 4
b1011 #
b1011 %
b1011 -
#320000
b110001 )
b110001 0
b100 &
b100 5
b1110 ,
b1110 .
b1110 /
b1110 1
b1110 4
b1001 #
b1001 %
b1001 -
#330000
b110000 )
b110000 0
b101 &
b101 5
b1111 ,
b1111 .
b1111 /
b1111 1
b1111 4
b1000 #
b1000 %
b1000 -
