src/design/module_display.sv
//Este modulo controla los datos enviados a los puertos del display

module display #(

    input logic [3 : 0] binary_code,      //Entrada: Codigo en binario
    output logic [6 : 0] display_code     //Salida: Codigo para el display
);

    //Segmento A:
    assign display_code[0] = ~((~binary_code[3] & ~binary_code[2] & ~binary_code[1] &  binary_code[0]) |
                              (~binary_code[3] &  binary_code[2] & ~binary_code[1] & ~binary_code[0]) |
                              ( binary_code[3] & ~binary_code[2] &  binary_code[1] &  binary_code[0]) |
                              ( binary_code[3] &  binary_code[2] & ~binary_code[1] &  binary_code[0]));

    //Segmento B:
    assign display_code[1] = ~((~binary_code[3] &  binary_code[2] & ~binary_code[1] &  binary_code[0]) | 
                              ( binary_code[3] &  binary_code[1] &  binary_code[0]) |
                              ( binary_code[2] &  binary_code[1] & ~binary_code[0]) |
                              ( binary_code[3] &  binary_code[2] & ~binary_code[0]));

    //Segmento C:
    assign display_code[2] = ~((~binary_code[3] & ~binary_code[2] &  binary_code[1] & ~binary_code[0]) | 
                              ( binary_code[3] &  binary_code[2] &  binary_code[1]) |
                              ( binary_code[3] &  binary_code[2] & ~binary_code[0]));

    //Segmento D:
    assign display_code[3] = ~((~binary_code[3] & ~binary_code[2] & ~binary_code[1] &  binary_code[0]) | 
                              (~binary_code[3] &  binary_code[2] & ~binary_code[1] & ~binary_code[0]) |
                              ( binary_code[2] &  binary_code[1] &  binary_code[0]) |
                              ( binary_code[3] & ~binary_code[2] &  binary_code[1] & ~binary_code[0]));

    //Segmento E:
    assign display_code[4] = ~((~binary_code[3] &  binary_code[0]) | 
                              (~binary_code[3] &  binary_code[2] & ~binary_code[1]) |
                              (~binary_code[2] & ~binary_code[1] &  binary_code[0]));

    //Segmento F:
    assign display_code[5] = ~((~binary_code[3] & ~binary_code[2] &  binary_code[0]) | 
                              (~binary_code[3] & ~binary_code[2] &  binary_code[1]) |
                              (~binary_code[3] &  binary_code[1] &  binary_code[0]) |
                              ( binary_code[3] &  binary_code[2] & ~binary_code[1] &  binary_code[0]));

    //Segmento G:
    assign display_code[6] = ~((~binary_code[3] & ~binary_code[2] & ~binary_code[1]) |
                              ( binary_code[3] &  binary_code[2] & ~binary_code[1] & ~binary_code[0]) |
                              (~binary_code[3] &  binary_code[2] &  binary_code[1] &  binary_code[0]));
endmodule

src/design/module_comparator.sv
//Este modulo compara si el numero binario es mayor o menor a 9

module comparator (

    input logic [3 : 0] binary_code,     
    output logic y
 
);
//1. Comprobar si el binario es mayor o menor a 1001 (9) 
//0 -> <9 and 1 -> >9
 assign y = binary_code[3] & (binary_code[2] | binary_code[1]);


endmodule

src/design/module_units.sv
//Extrae la unidad en numeros binarios mayores a 9

module units (
    input logic [3 : 0] binary_code,      //Entrada: codigo binario mayor a 9
    output logic [3 : 0] binary_units      //Salida: unidades del numero binario de entrada

);

assign binary_units = binary_code - 4'b1010;

endmodule

src/design/gray_decoder.sv
module gray_decoder (
    input logic [3:0] gray,   // Entrada en Gray
    output logic [3:0] binary // Salida en Binario
);

    // Conversión de Gray a Binario
    assign binary[3] = gray[3];                // El bit más significativo es igual
    assign binary[2] = gray[3] ^ gray[2];      // bit2 = bit3 ^ bit2
    assign binary[1] = binary[2] ^ gray[1];   // bit1 = bit2 ^ bit1
    assign binary[0] = binary[1] ^ gray[0];   // bit0 = bit1 ^ bit0

endmodule

src/design/module_top.sv
//Este módulo interconecta los tres sub módulos 

module top (

    input logic [3 : 0] gray_code,       //Entrada: codigo Gray
    input logic show_decades,            //Entrada: boton de decenas o unidades
    output logic [6 : 0] display_code   //Salida: codigo al display
);

    logic [3 : 0] binary_code;      //Almacena temporalmente el codigo binario
    logic [3 : 0] units_code;       //Almacena las unidades temporalmente
    logic [3 : 0] decades_code;        //Almacena las decenas temporalmente
    logic [3 : 0] selected_code;    //Guarda el codigo a entregar en el module_display
    logic show_units;               //Almacena 0 si <9 o 1 si >9

    gray_decoder u_gray_decoder (
        .gray(gray_code),           //Se recibe el código Gray y se envía a gray_decoder.sv
        .binary(binary_code)        //Recoge el codigo binario ya convertido y lo almacena
    );

    units u_module_units(
        .binary_code(binary_code),  //Envia el binario para separar unidades
        .binary_units(units_code)   //Almacena las unidades extraides
    );

    comparator u_module_comparator(
        .binary_code(binary_code),      //Le envia la señal en binario al module_display
        .y(show_units)                  //Indica si n<9 o n>9
    );

    //mux que va con el comparador (escoje que binario pasa al module display)
    assign decades_code = (show_units) ? 4'b0001 : 4'b0000; //Vale 1 si show_units == 1 y 0 si show_units == 0
    assign selected_code = (show_decades) ? decades_code : (show_units ? units_code : binary_code); //Determina el codigo a enviar

    display u_module_display(
        .binary_code(selected_code),
        .display_code(display_code)
    );
endmodule

src/sim/tb_module_top.sv
`timescale 1ns / 1ps

module tb_top;

    // Entradas para el módulo 'top'
    reg [3:0] gray_code;
    reg show_decades;

    // Salida del módulo 'top'
    wire [6:0] display_code;

    // Instancia del módulo 'top'
    top uut (
        .gray_code(gray_code),
        .show_decades(show_decades),
        .display_code(display_code)
    );

    // Generación de señales de prueba
    initial begin
        // Inicialización
        gray_code = 4'b0000;
        show_decades = 0;

        // Pruebas con show_decades = 0
        // Verifica que el display muestra el valor binario correcto para valores de 0 a 15
        #10 gray_code = 4'b0000; // 0
        #10 gray_code = 4'b0001; // 1
        #10 gray_code = 4'b0010; // 2
        #10 gray_code = 4'b0011; // 3
        #10 gray_code = 4'b0100; // 4
        #10 gray_code = 4'b0101; // 5
        #10 gray_code = 4'b0110; // 6
        #10 gray_code = 4'b0111; // 7
        #10 gray_code = 4'b1000; // 8
        #10 gray_code = 4'b1001; // 9
        #10 gray_code = 4'b1010; // 10
        #10 gray_code = 4'b1011; // 11
        #10 gray_code = 4'b1100; // 12
        #10 gray_code = 4'b1101; // 13
        #10 gray_code = 4'b1110; // 14
        #10 gray_code = 4'b1111; // 15

        // Cambio de show_decades a 1
        #10 show_decades = 1;

        // Pruebas con show_decades = 1
        // Verifica que el display muestra las decenas cuando el valor es mayor a 9
        #10 gray_code = 4'b0000; // 0
        #10 gray_code = 4'b0001; // 1
        #10 gray_code = 4'b0010; // 2
        #10 gray_code = 4'b0011; // 3
        #10 gray_code = 4'b0100; // 4
        #10 gray_code = 4'b0101; // 5
        #10 gray_code = 4'b0110; // 6
        #10 gray_code = 4'b0111; // 7
        #10 gray_code = 4'b1000; // 8
        #10 gray_code = 4'b1001; // 9
        #10 gray_code = 4'b1010; // 10
        #10 gray_code = 4'b1011; // 11
        #10 gray_code = 4'b1100; // 12
        #10 gray_code = 4'b1101; // 13
        #10 gray_code = 4'b1110; // 14
        #10 gray_code = 4'b1111; // 15

        // Finalización de la simulación
        #10 $finish;
    end

    // Monitorear las señales
    initial begin
        $monitor("At time %t: gray_code = %b, show_decades = %b, display_code = %b",
                 $time, gray_code, show_decades, display_code);
    end

    // Dump de la simulación para VCD
    initial begin
        $dumpfile("tb_top_simulation.vcd");
        $dumpvars(0, tb_top);
    end

endmodule

src/build/tb_top_simulation.vcd
$date
	Sun Aug 25 11:07:51 2024
$end
$version
	Icarus Verilog
$end
$timescale
	1ps
$end
$scope module tb_top $end
$var wire 7 ! display_code [6:0] $end
$var reg 4 " gray_code [3:0] $end
$var reg 1 # show_decades $end
$scope module uut $end
$var wire 4 $ gray_code [3:0] $end
$var wire 1 # show_decades $end
$var wire 4 % units_code [3:0] $end
$var wire 1 & show_units $end
$var wire 4 ' selected_code [3:0] $end
$var wire 7 ( display_code [6:0] $end
$var wire 4 ) decades_code [3:0] $end
$var wire 4 * binary_code [3:0] $end
$scope module u_gray_decoder $end
$var wire 4 + gray [3:0] $end
$var wire 4 , binary [3:0] $end
$upscope $end
$scope module u_module_comparator $end
$var wire 4 - binary_code [3:0] $end
$var wire 1 & y $end
$upscope $end
$scope module u_module_display $end
$var wire 4 . binary_code [3:0] $end
$var wire 7 / display_code [6:0] $end
$upscope $end
$scope module u_module_units $end
$var wire 4 0 binary_code [3:0] $end
$var wire 4 1 binary_units [3:0] $end
$upscope $end
$upscope $end
$upscope $end
$enddefinitions $end
$comment Show the parameter values. $end
$dumpall
$end
#0
$dumpvars
b110 1
b0 0
b1111110 /
b0 .
b0 -
b0 ,
b0 +
b0 *
b0 )
b1111110 (
b0 '
0&
b110 %
b0 $
0#
b0 "
b1111110 !
$end
#20000
b110000 !
b110000 (
b110000 /
b1 '
b1 .
b111 %
b111 1
b1 *
b1 ,
b1 -
b1 0
b1 "
b1 $
b1 +
#30000
b1111001 !
b1111001 (
b1111001 /
b11 '
b11 .
b1001 %
b1001 1
b11 *
b11 ,
b11 -
b11 0
b10 "
b10 $
b10 +
#40000
b1101101 !
b1101101 (
b1101101 /
b10 '
b10 .
b1000 %
b1000 1
b10 *
b10 ,
b10 -
b10 0
b11 "
b11 $
b11 +
#50000
b1110000 !
b1110000 (
b1110000 /
b111 '
b111 .
b1101 %
b1101 1
b111 *
b111 ,
b111 -
b111 0
b100 "
b100 $
b100 +
#60000
b1011111 !
b1011111 (
b1011111 /
b110 '
b110 .
b1100 %
b1100 1
b110 *
b110 ,
b110 -
b110 0
b101 "
b101 $
b101 +
#70000
b110011 !
b110011 (
b110011 /
b100 '
b100 .
b1010 %
b1010 1
b100 *
b100 ,
b100 -
b100 0
b110 "
b110 $
b110 +
#80000
b1011011 !
b1011011 (
b1011011 /
b101 '
b101 .
b1011 %
b1011 1
b101 *
b101 ,
b101 -
b101 0
b111 "
b111 $
b111 +
#90000
b1011011 !
b1011011 (
b1011011 /
b1 )
1&
b101 '
b101 .
b101 %
b101 1
b1111 *
b1111 ,
b1111 -
b1111 0
b1000 "
b1000 $
b1000 +
#100000
b110011 !
b110011 (
b110011 /
b100 '
b100 .
b100 %
b100 1
b1110 *
b1110 ,
b1110 -
b1110 0
b1001 "
b1001 $
b1001 +
#110000
b1101101 !
b1101101 (
b1101101 /
b10 '
b10 .
b10 %
b10 1
b1100 *
b1100 ,
b1100 -
b1100 0
b1010 "
b1010 $
b1010 +
#120000
b1111001 !
b1111001 (
b1111001 /
b11 '
b11 .
b11 %
b11 1
b1101 *
b1101 ,
b1101 -
b1101 0
b1011 "
b1011 $
b1011 +
#130000
b1111111 !
b1111111 (
b1111111 /
b0 )
0&
b1000 '
b1000 .
b1110 %
b1110 1
b1000 *
b1000 ,
b1000 -
b1000 0
b1100 "
b1100 $
b1100 +
#140000
b1110011 !
b1110011 (
b1110011 /
b1001 '
b1001 .
b1111 %
b1111 1
b1001 *
b1001 ,
b1001 -
b1001 0
b1101 "
b1101 $
b1101 +
#150000
b110000 !
b110000 (
b110000 /
b1 )
1&
b1 '
b1 .
b1 %
b1 1
b1011 *
b1011 ,
b1011 -
b1011 0
b1110 "
b1110 $
b1110 +
#160000
b1111110 !
b1111110 (
b1111110 /
b0 '
b0 .
b0 %
b0 1
b1010 *
b1010 ,
b1010 -
b1010 0
b1111 "
b1111 $
b1111 +
#170000
b110000 !
b110000 (
b110000 /
b1 '
b1 .
1#
#180000
b1111110 !
b1111110 (
b1111110 /
b0 '
b0 .
b0 )
0&
b110 %
b110 1
b0 *
b0 ,
b0 -
b0 0
b0 "
b0 $
b0 +
#190000
b111 %
b111 1
b1 *
b1 ,
b1 -
b1 0
b1 "
b1 $
b1 +
#200000
b1001 %
b1001 1
b11 *
b11 ,
b11 -
b11 0
b10 "
b10 $
b10 +
#210000
b1000 %
b1000 1
b10 *
b10 ,
b10 -
b10 0
b11 "
b11 $
b11 +
#220000
b1101 %
b1101 1
b111 *
b111 ,
b111 -
b111 0
b100 "
b100 $
b100 +
#230000
b1100 %
b1100 1
b110 *
b110 ,
b110 -
b110 0
b101 "
b101 $
b101 +
#240000
b1010 %
b1010 1
b100 *
b100 ,
b100 -
b100 0
b110 "
b110 $
b110 +
#250000
b1011 %
b1011 1
b101 *
b101 ,
b101 -
b101 0
b111 "
b111 $
b111 +
#260000
b110000 !
b110000 (
b110000 /
b1 '
b1 .
b1 )
1&
b101 %
b101 1
b1111 *
b1111 ,
b1111 -
b1111 0
b1000 "
b1000 $
b1000 +
#270000
b100 %
b100 1
b1110 *
b1110 ,
b1110 -
b1110 0
b1001 "
b1001 $
b1001 +
#280000
b10 %
b10 1
b1100 *
b1100 ,
b1100 -
b1100 0
b1010 "
b1010 $
b1010 +
#290000
b11 %
b11 1
b1101 *
b1101 ,
b1101 -
b1101 0
b1011 "
b1011 $
b1011 +
#300000
b1111110 !
b1111110 (
b1111110 /
b0 '
b0 .
b0 )
0&
b1110 %
b1110 1
b1000 *
b1000 ,
b1000 -
b1000 0
b1100 "
b1100 $
b1100 +
#310000
b1111 %
b1111 1
b1001 *
b1001 ,
b1001 -
b1001 0
b1101 "
b1101 $
b1101 +
#320000
b110000 !
b110000 (
b110000 /
b1 '
b1 .
b1 )
1&
b1 %
b1 1
b1011 *
b1011 ,
b1011 -
b1011 0
b1110 "
b1110 $
b1110 +
#330000
b0 %
b0 1
b1010 *
b1010 ,
b1010 -
b1010 0
b1111 "
b1111 $
b1111 +
